{
  "version": 1,
  "people": [
    {
      "id": "sample-person",
      "displayName": "Sample Person",
      "createdAt": "2026-06-03T13:28:15.118Z",
      "updatedAt": "2026-06-03T13:28:15.118Z"
    }
  ],
  "documents": [
    {
      "id": "linkedin_0cf875a21e801d77f2cbfe4e",
      "personId": "sample-person",
      "platform": "linkedin",
      "kind": "profile",
      "title": "Sample Person",
      "text": "Name: Sample Person. Headline: Founder and engineering leader. About: I write about remote work, async teams, and practical product engineering.. Industry: Software. Location: San Francisco",
      "externalId": "Sample Person",
      "sourceFile": "samples/linkedin/Profile.csv",
      "contentHash": "0cf875a21e801d77f2cbfe4e",
      "metadata": {
        "industry": "Software",
        "location": "San Francisco"
      },
      "createdAt": "2026-06-03T13:28:15.112Z",
      "updatedAt": "2026-06-03T13:28:15.112Z"
    },
    {
      "id": "linkedin_572a6f9bd442a806eb5dd57f",
      "personId": "sample-person",
      "platform": "linkedin",
      "kind": "post",
      "title": "LinkedIn post",
      "text": "Remote teams work when expectations are explicit, writing is valued, and managers measure outcomes instead of desk time.",
      "externalId": "2025-01-04:Remote teams work when expectations are explicit, writing is valued, and managers measure outcomes instead of desk time.",
      "authoredAt": "2025-01-04",
      "uri": "https://www.linkedin.com/feed/update/urn:li:activity:1",
      "sourceFile": "samples/linkedin/Shares.csv",
      "contentHash": "572a6f9bd442a806eb5dd57f",
      "metadata": {
        "visibility": "Public"
      },
      "createdAt": "2026-06-03T13:28:15.114Z",
      "updatedAt": "2026-06-03T13:28:15.114Z"
    },
    {
      "id": "linkedin_76dceca3f0f394b43c3c7f42",
      "personId": "sample-person",
      "platform": "linkedin",
      "kind": "post",
      "title": "LinkedIn post",
      "text": "I prefer hybrid rituals for trust building, but deep engineering work is usually better when people have quiet remote blocks.",
      "externalId": "2025-03-12:I prefer hybrid rituals for trust building, but deep engineering work is usually better when people have quiet remote blocks.",
      "authoredAt": "2025-03-12",
      "uri": "https://www.linkedin.com/feed/update/urn:li:activity:2",
      "sourceFile": "samples/linkedin/Shares.csv",
      "contentHash": "76dceca3f0f394b43c3c7f42",
      "metadata": {
        "visibility": "Public"
      },
      "createdAt": "2026-06-03T13:28:15.115Z",
      "updatedAt": "2026-06-03T13:28:15.115Z"
    },
    {
      "id": "twitter_6e64a394d4acaf3128920ac3",
      "personId": "sample-person",
      "platform": "twitter",
      "kind": "post",
      "title": "Twitter/X post",
      "text": "Remote work is not a perk; it is an operating system. The hard part is documentation and trust.",
      "externalId": "1001",
      "authoredAt": "Wed Jan 08 12:00:00 +0000 2025",
      "sourceFile": "samples/twitter/tweet.js",
      "contentHash": "6e64a394d4acaf3128920ac3",
      "metadata": {
        "favoriteCount": "12",
        "retweetCount": "2"
      },
      "createdAt": "2026-06-03T13:28:15.116Z",
      "updatedAt": "2026-06-03T13:28:15.116Z"
    },
    {
      "id": "twitter_2b10ae9e9a98912b47b13141",
      "personId": "sample-person",
      "platform": "twitter",
      "kind": "post",
      "title": "Twitter/X post",
      "text": "The best distributed teams invest in onboarding docs before buying another meeting tool.",
      "externalId": "1003",
      "authoredAt": "Fri Jan 10 12:00:00 +0000 2025",
      "sourceFile": "samples/twitter/tweet.js",
      "contentHash": "2b10ae9e9a98912b47b13141",
      "metadata": {
        "favoriteCount": "9",
        "retweetCount": "1"
      },
      "createdAt": "2026-06-03T13:28:15.116Z",
      "updatedAt": "2026-06-03T13:28:15.116Z"
    },
    {
      "id": "instagram_6f8e1833bea9c4824926877b",
      "personId": "sample-person",
      "platform": "instagram",
      "kind": "caption",
      "title": "Instagram caption",
      "text": "My favorite remote setup is boring: clear priorities, fewer meetings, and a written handoff.",
      "externalId": "media/posts/202501/remote-desk.jpg",
      "authoredAt": "2025-01-10T12:00:00.000Z",
      "uri": "media/posts/202501/remote-desk.jpg",
      "sourceFile": "samples/instagram/posts_1.json",
      "contentHash": "6f8e1833bea9c4824926877b",
      "metadata": {
        "mediaPath": "media/posts/202501/remote-desk.jpg"
      },
      "createdAt": "2026-06-03T13:28:15.117Z",
      "updatedAt": "2026-06-03T13:28:15.117Z"
    },
    {
      "id": "instagram_a30adb37ebf70c844faea47e",
      "personId": "sample-person",
      "platform": "instagram",
      "kind": "caption",
      "title": "Instagram caption",
      "text": "Offsites are useful for relationships, not for pretending every day needs to be in person.",
      "externalId": "media/posts/202502/team-offsite.jpg",
      "authoredAt": "2025-02-10T12:00:00.000Z",
      "uri": "media/posts/202502/team-offsite.jpg",
      "sourceFile": "samples/instagram/posts_1.json",
      "contentHash": "a30adb37ebf70c844faea47e",
      "metadata": {
        "mediaPath": "media/posts/202502/team-offsite.jpg"
      },
      "createdAt": "2026-06-03T13:28:15.117Z",
      "updatedAt": "2026-06-03T13:28:15.117Z"
    }
  ],
  "chunks": [
    {
      "id": "chunk_b85bb169e4be610a74aaa000",
      "documentId": "linkedin_0cf875a21e801d77f2cbfe4e",
      "personId": "sample-person",
      "platform": "linkedin",
      "kind": "profile",
      "text": "Name: Sample Person. Headline: Founder and engineering leader. About: I write about remote work, async teams, and practical product engineering.. Industry: Software. Location: San Francisco",
      "ordinal": 0,
      "tokenCount": 21,
      "contentHash": "b85bb169e4be610a74aaa000",
      "sourceTitle": "Sample Person",
      "metadata": {
        "industry": "Software",
        "location": "San Francisco",
        "sourceFile": "samples/linkedin/Profile.csv",
        "externalId": "Sample Person"
      },
      "embedding": [
        0,
        0,
        0,
        0,
        0,
        0,
        0,
        0,
        0,
        0,
        0,
        0,
        0,
        0,
        0,
        0,
        0.190866,
        0,
        0,
        0,
        0,
        0,
        0,
        0,
        0,
        0,
        0,
        0,
        0,
        0,
        0,
        0,
        0,
        0,
        0.066803,
        0,
        0,
        0,
        0,
        0,
        0,
        0,
        0,
        0,
        -0.190866,
        0,
        0,
        0,
        -0.381732,
        0,
        0,
        0,
        -0.190866,
        0,
        0,
        0,
        0,
        0,
        0,
        0,
        0,
        0,
        -0.381732,
        0,
        0,
        0,
        0,
        0,
        0.066803,
        0,
        0.066803,
        0,
        0,
        0,
        0,
        0,
        0,
        0,
        0,
        0,
        0,
        0,
        0,
        0,
        0,
        0,
        0,
        0,
        0,
        0,
        0,
        0,
        -0.190866,
        0,
        0,
        0,
        0.190866,
        0,
        0,
        0,
        0.066803,
        0,
        0,
        -0.066803,
        0,
        0,
        0.066803,
        0,
        0,
        0,
        0,
        0,
        0,
        0.066803,
        0,
        0,
        0,
        0,
        0,
        0,
        0,
        0,
        0,
        0,
        0,
        0,
        0,
        0,
        0,
        0,
        0,
        0,
        0,
        0,
        0,
        0,
        0,
        0,
        0,
        0,
        0,
        0,
        0,
        0.066803,
        0,
        0,
        0,
        0,
        -0.066803,
        -0.190866,
        0,
        0,
        0.066803,
        -0.066803,
        0,
        0,
        0,
        0,
        0,
        0,
        0,
        0,
        0,
        0,
        0,
        0,
        0,
        -0.190866,
        0,
        0,
        0,
        0,
        0,
        0,
        0,
        0,
        0,
        -0.066803,
        0,
        0,
        0,
        0,
        0,
        0,
        0,
        0.066803,
        0,
        0,
        0,
        0,
        0,
        0,
        0,
        -0.190866,
        0,
        0,
        0,
        0,
        0,
        0,
        0,
        0,
        0,
        0,
        -0.066803,
        0,
        -0.066803,
        0,
        0,
        0,
        0,
        -0.190866,
        0,
        -0.066803,
        0,
        0,
        0,
        0,
        0,
        0,
        0,
        0,
        0,
        0,
        0,
        0,
        0,
        0,
        -0.190866,
        0,
        -0.190866,
        0,
        0,
        0,
        0,
        0,
        0,
        0.190866,
        0,
        0,
        0,
        0,
        0,
        0,
        0,
        0,
        0,
        0,
        0,
        0,
        0,
        0,
        0,
        0,
        0,
        0,
        0,
        0,
        0,
        0,
        0,
        0,
        0,
        0,
        0,
        0,
        0,
        0,
        0,
        0,
        0,
        -0.190866,
        0,
        0,
        0,
        0,
        0,
        0,
        0,
        0,
        0,
        0,
        0,
        0,
        0,
        0,
        0,
        0,
        0,
        0,
        0,
        0,
        0,
        0,
        0.190866,
        0,
        0,
        0,
        0,
        0,
        0,
        0,
        0,
        0,
        0,
        0,
        0,
        0,
        0,
        0,
        0,
        0,
        0,
        0,
        0,
        0,
        0,
        0,
        0,
        0.190866,
        0,
        0,
        0,
        0,
        0,
        0,
        0,
        0,
        0,
        0.190866,
        0,
        0,
        0.066803,
        0,
        -0.066803,
        0,
        0,
        0,
        0,
        0,
        0,
        0,
        0,
        0,
        0,
        0,
        0,
        0,
        0,
        0,
        0,
        0,
        0,
        0,
        0,
        0,
        0,
        0,
        0,
        -0.066803,
        0,
        0,
        0,
        0,
        0,
        0,
        0,
        0,
        -0.190866,
        0,
        0,
        0,
        0,
        0,
        0,
        0,
        0,
        0.066803,
        0,
        0,
        0,
        0,
        0,
        0
      ],
      "embeddingModel": "local-hashing-v1",
      "embeddingDimensions": 384,
      "insertedAt": "2026-06-03T13:28:15.120Z"
    },
    {
      "id": "chunk_bf6a1180b9566ece98559cb9",
      "documentId": "linkedin_572a6f9bd442a806eb5dd57f",
      "personId": "sample-person",
      "platform": "linkedin",
      "kind": "post",
      "text": "Remote teams work when expectations are explicit, writing is valued, and managers measure outcomes instead of desk time.",
      "ordinal": 0,
      "tokenCount": 14,
      "contentHash": "bf6a1180b9566ece98559cb9",
      "authoredAt": "2025-01-04",
      "uri": "https://www.linkedin.com/feed/update/urn:li:activity:1",
      "sourceTitle": "LinkedIn post",
      "metadata": {
        "visibility": "Public",
        "sourceFile": "samples/linkedin/Shares.csv",
        "externalId": "2025-01-04:Remote teams work when expectations are explicit, writing is valued, and managers measure outcomes instead of desk time."
      },
      "embedding": [
        0,
        -0.086711,
        0,
        0,
        0,
        0,
        0,
        0,
        0,
        0,
        -0.086711,
        0,
        0,
        0,
        0,
        0,
        0,
        0,
        0,
        0,
        0,
        0,
        0,
        0,
        0,
        0,
        0,
        0,
        0,
        0,
        0,
        0,
        0,
        0,
        0,
        0,
        0,
        0,
        0,
        0,
        0,
        0,
        0,
        0,
        0,
        0,
        0,
        0,
        0,
        0,
        0,
        0,
        0,
        0,
        0,
        0,
        -0.247746,
        0,
        0,
        0,
        0,
        0.086711,
        0,
        0,
        0,
        0,
        -0.086711,
        0,
        -0.086711,
        0,
        0.086711,
        0,
        0,
        0.247746,
        0,
        0,
        0,
        0,
        0,
        0,
        0,
        0,
        0,
        0,
        0,
        0,
        0,
        0,
        0,
        0,
        0,
        0,
        0,
        0,
        0,
        0.247746,
        0.247746,
        0,
        0,
        0,
        0,
        0,
        0,
        0,
        0,
        0,
        0,
        0,
        0,
        0,
        0,
        0,
        0,
        0,
        0,
        0,
        0,
        -0.086711,
        0,
        0,
        0,
        0,
        0,
        0,
        0,
        0,
        0,
        0,
        0,
        0,
        0,
        0,
        0,
        0,
        0,
        0,
        0,
        0,
        0,
        0,
        0,
        0,
        0,
        0,
        0,
        0,
        0,
        0,
        0,
        0,
        0,
        0,
        0,
        0,
        0,
        0,
        0,
        0,
        0,
        0,
        0,
        0,
        0,
        0,
        0,
        0,
        0,
        0,
        0,
        0,
        0,
        0,
        0,
        -0.247746,
        0,
        0,
        0,
        0,
        0,
        0,
        0,
        0,
        0,
        0.086711,
        0,
        0,
        0,
        0,
        0,
        0,
        0,
        0,
        -0.247746,
        0,
        0,
        0,
        0,
        0,
        0,
        0,
        0,
        0,
        0,
        0,
        0,
        0,
        0,
        -0.334457,
        0,
        0,
        0,
        -0.247746,
        0,
        0,
        0,
        0,
        0,
        0,
        0,
        0,
        0,
        0,
        0,
        0,
        0,
        0,
        0,
        0,
        0,
        0,
        0,
        0,
        0,
        0,
        0,
        0,
        0,
        0.247746,
        0,
        0,
        0,
        0.247746,
        0,
        0,
        0,
        0,
        0,
        0,
        0,
        0,
        0,
        0,
        0,
        0,
        0,
        0,
        0,
        0,
        0,
        0,
        0,
        0,
        0,
        0,
        0,
        0.086711,
        0,
        0,
        0,
        0,
        0,
        0,
        0,
        0,
        0,
        0,
        0,
        0,
        0,
        0,
        0,
        0.247746,
        0,
        0,
        0,
        0,
        0,
        0,
        0,
        0,
        0.247746,
        0,
        0,
        0,
        0,
        0,
        0,
        0,
        0,
        0,
        0,
        0,
        0,
        0,
        0,
        0,
        0,
        0,
        0,
        0,
        0,
        0,
        0,
        0,
        0,
        0,
        0,
        0,
        0,
        0,
        0,
        0,
        0,
        0,
        0,
        0,
        0,
        0,
        0,
        0,
        0,
        0,
        0,
        0,
        0,
        0,
        0,
        0,
        0,
        0,
        0,
        0,
        0,
        0,
        0,
        0,
        0,
        -0.086711,
        0,
        0,
        0,
        -0.086711,
        0,
        0,
        0,
        0,
        0.247746,
        0,
        0,
        0,
        0,
        0,
        0.247746,
        0,
        0,
        0,
        0,
        0,
        0,
        0,
        0,
        -0.086711,
        0,
        0,
        0,
        0,
        0,
        0,
        0,
        0,
        0,
        0,
        0,
        0
      ],
      "embeddingModel": "local-hashing-v1",
      "embeddingDimensions": 384,
      "insertedAt": "2026-06-03T13:28:15.120Z"
    },
    {
      "id": "chunk_1013d958eb83b7fe724fa31b",
      "documentId": "linkedin_76dceca3f0f394b43c3c7f42",
      "personId": "sample-person",
      "platform": "linkedin",
      "kind": "post",
      "text": "I prefer hybrid rituals for trust building, but deep engineering work is usually better when people have quiet remote blocks.",
      "ordinal": 0,
      "tokenCount": 14,
      "contentHash": "1013d958eb83b7fe724fa31b",
      "authoredAt": "2025-03-12",
      "uri": "https://www.linkedin.com/feed/update/urn:li:activity:2",
      "sourceTitle": "LinkedIn post",
      "metadata": {
        "visibility": "Public",
        "sourceFile": "samples/linkedin/Shares.csv",
        "externalId": "2025-03-12:I prefer hybrid rituals for trust building, but deep engineering work is usually better when people have quiet remote blocks."
      },
      "embedding": [
        0,
        0,
        0,
        0,
        0,
        0,
        0,
        0,
        0,
        0,
        -0.088636,
        -0.088636,
        0,
        0,
        0,
        0,
        0,
        0,
        0,
        0,
        0,
        0,
        0,
        0,
        0,
        0,
        0,
        0,
        0,
        0,
        0,
        0,
        0,
        0,
        0,
        0,
        0,
        0,
        0,
        0,
        0,
        0,
        0,
        0,
        0,
        0,
        0,
        0,
        -0.253246,
        0,
        0,
        0,
        0,
        0,
        0,
        0,
        0,
        0,
        0,
        0,
        0,
        0,
        0,
        0,
        0,
        0,
        0,
        0.253246,
        0,
        0,
        0,
        0,
        0,
        0,
        0,
        0,
        0,
        0,
        0,
        0,
        0,
        0,
        0,
        0,
        0,
        0,
        0,
        0,
        0,
        0,
        -0.088636,
        0,
        0,
        0,
        0,
        0,
        0.253246,
        0,
        0,
        0,
        0,
        0,
        0,
        0,
        0,
        0,
        0,
        0,
        0,
        0,
        -0.088636,
        0,
        0.088636,
        0,
        0,
        0,
        0,
        0.253246,
        0,
        0,
        0,
        0,
        0,
        0,
        0,
        0,
        0,
        0,
        0,
        0,
        0,
        0,
        0,
        0,
        0,
        0,
        0,
        0,
        0,
        0,
        0,
        0,
        -0.088636,
        0,
        0,
        0,
        0.253246,
        0,
        0,
        0,
        0,
        0,
        0,
        0,
        0,
        0,
        0,
        0,
        0,
        0,
        0,
        0,
        0,
        0,
        0,
        0,
        0,
        0,
        0,
        0.088636,
        0,
        0,
        0,
        0,
        0,
        0,
        0,
        0,
        0,
        -0.253246,
        0,
        0,
        0,
        0,
        0,
        0,
        0,
        0,
        0,
        0,
        0,
        0,
        0,
        0,
        0,
        0,
        0,
        0,
        0,
        0,
        0,
        0,
        0,
        0,
        0,
        0,
        0,
        0,
        0,
        0,
        0,
        -0.253246,
        0,
        0,
        -0.088636,
        0,
        -0.088636,
        0,
        0,
        0,
        0,
        0,
        0,
        0,
        0,
        0,
        0,
        0,
        0.088636,
        0,
        0,
        0,
        0,
        0,
        0,
        0,
        0,
        0,
        0,
        0,
        0,
        0,
        0,
        0,
        0,
        -0.253246,
        0,
        0.253246,
        0,
        0,
        0,
        0,
        0,
        0,
        0,
        0,
        0,
        0,
        0,
        0,
        0,
        0,
        0.088636,
        0,
        0,
        0,
        0.088636,
        0,
        0,
        0,
        0,
        0.253246,
        0,
        0,
        0,
        0,
        0,
        0,
        0,
        -0.253246,
        0,
        0.253246,
        0,
        0,
        0,
        0,
        0,
        0,
        0,
        0,
        0,
        0,
        0,
        0,
        0,
        0,
        0,
        0,
        0,
        0,
        0,
        0,
        0,
        0,
        0,
        0,
        0,
        0,
        0,
        0,
        0,
        0,
        0,
        0,
        0,
        0,
        0,
        0,
        0,
        0,
        0,
        0,
        0,
        0,
        0,
        0,
        0,
        0,
        -0.088636,
        0,
        0,
        0,
        0,
        0,
        0,
        0,
        0,
        0,
        0,
        0,
        0,
        0,
        0,
        0,
        0,
        0,
        0,
        0,
        0,
        0,
        0,
        0,
        0,
        0,
        0,
        -0.253246,
        0,
        0,
        0,
        0,
        0,
        0,
        0,
        0,
        0,
        0,
        0,
        -0.253246,
        0,
        0,
        0,
        0,
        0,
        0,
        0,
        0,
        0,
        0,
        0,
        0,
        0,
        0,
        0,
        0
      ],
      "embeddingModel": "local-hashing-v1",
      "embeddingDimensions": 384,
      "insertedAt": "2026-06-03T13:28:15.120Z"
    },
    {
      "id": "chunk_a0a96dc670d1714ae7ca2ada",
      "documentId": "twitter_6e64a394d4acaf3128920ac3",
      "personId": "sample-person",
      "platform": "twitter",
      "kind": "post",
      "text": "Remote work is not a perk; it is an operating system. The hard part is documentation and trust.",
      "ordinal": 0,
      "tokenCount": 10,
      "contentHash": "a0a96dc670d1714ae7ca2ada",
      "authoredAt": "Wed Jan 08 12:00:00 +0000 2025",
      "sourceTitle": "Twitter/X post",
      "metadata": {
        "favoriteCount": "12",
        "retweetCount": "2",
        "sourceFile": "samples/twitter/tweet.js",
        "externalId": "1001"
      },
      "embedding": [
        0,
        0,
        0,
        0,
        0,
        0,
        0,
        0,
        0,
        0,
        0,
        0,
        0,
        0,
        0,
        0,
        0,
        0,
        0,
        0,
        0,
        0,
        0,
        0,
        0,
        0,
        0,
        0,
        0,
        0,
        0,
        0,
        0,
        0,
        0,
        0,
        0,
        0,
        0,
        0,
        0.300116,
        0,
        0,
        0,
        0,
        0,
        0,
        0,
        0,
        0,
        0,
        0,
        0,
        0.105041,
        0,
        0,
        0,
        0,
        0,
        0,
        0,
        0,
        0,
        0,
        0,
        0,
        0,
        0,
        0,
        0,
        0,
        0,
        0,
        0,
        0,
        0,
        0,
        0,
        0,
        0,
        0,
        0,
        0,
        0,
        0,
        0,
        0,
        0,
        0,
        0,
        0,
        0,
        -0.300116,
        0,
        0,
        0,
        0.300116,
        0,
        0.105041,
        0,
        0,
        0,
        0,
        0,
        0,
        0,
        0,
        0,
        0,
        0,
        0,
        0,
        0,
        0.105041,
        0,
        0,
        0,
        0,
        0,
        0,
        0,
        0,
        0,
        0,
        0,
        0,
        0,
        0,
        0,
        0,
        0,
        0,
        0,
        0,
        0,
        0,
        0,
        -0.105041,
        0,
        0,
        0,
        0,
        0,
        0,
        0,
        0,
        0,
        0,
        0,
        0,
        0,
        0,
        0,
        0,
        0,
        0,
        0,
        0,
        0,
        0,
        0,
        0,
        0,
        0,
        0,
        0,
        0,
        0,
        0,
        0,
        0,
        0,
        0,
        0,
        0,
        -0.105041,
        0,
        0,
        0,
        0,
        0,
        0,
        0,
        0,
        0,
        0,
        0,
        0,
        0,
        0,
        0,
        0,
        0,
        0,
        0,
        0,
        0,
        0,
        0,
        0,
        0,
        0,
        0,
        0,
        0,
        0,
        0,
        0,
        0,
        0,
        0,
        -0.300116,
        0,
        0,
        0,
        0,
        0,
        0,
        0,
        0,
        0,
        0,
        0,
        0,
        0,
        0,
        0,
        0,
        0,
        0,
        0,
        0,
        0.105041,
        0,
        0,
        0,
        0,
        0,
        0,
        0,
        0,
        0,
        0,
        0,
        0,
        -0.300116,
        0,
        0,
        0,
        0,
        0,
        0,
        0,
        0,
        0,
        0,
        0,
        0.300116,
        0,
        0,
        0,
        0,
        0,
        0,
        0,
        0,
        0.300116,
        0,
        0,
        0,
        0,
        0,
        0,
        0,
        0,
        0,
        0.300116,
        0,
        0,
        0,
        0,
        0,
        0,
        0,
        0.300116,
        0,
        0,
        0,
        0,
        0,
        0,
        0,
        0,
        0,
        0,
        0,
        0,
        0,
        0,
        0,
        -0.105041,
        0,
        0,
        0,
        0,
        0,
        0,
        0,
        0,
        0,
        0,
        0,
        0,
        0,
        0,
        0,
        0,
        0,
        0,
        0,
        0,
        0,
        0,
        0,
        0,
        0,
        0,
        0,
        0,
        0,
        0,
        0,
        0,
        0,
        0,
        0,
        0,
        0,
        0,
        0,
        0,
        0,
        0,
        0,
        0.105041,
        0,
        0,
        0,
        0,
        -0.300116,
        0,
        0,
        0,
        0,
        0,
        0,
        0,
        0,
        0,
        0,
        0,
        0,
        0,
        0,
        0,
        0,
        0,
        0,
        0.105041,
        0,
        0,
        0,
        0,
        0,
        0,
        0,
        0,
        0,
        0,
        0,
        0,
        0,
        0,
        0
      ],
      "embeddingModel": "local-hashing-v1",
      "embeddingDimensions": 384,
      "insertedAt": "2026-06-03T13:28:15.120Z"
    },
    {
      "id": "chunk_7129ba38c0206132ac6bbeca",
      "documentId": "twitter_2b10ae9e9a98912b47b13141",
      "personId": "sample-person",
      "platform": "twitter",
      "kind": "post",
      "text": "The best distributed teams invest in onboarding docs before buying another meeting tool.",
      "ordinal": 0,
      "tokenCount": 11,
      "contentHash": "7129ba38c0206132ac6bbeca",
      "authoredAt": "Fri Jan 10 12:00:00 +0000 2025",
      "sourceTitle": "Twitter/X post",
      "metadata": {
        "favoriteCount": "9",
        "retweetCount": "1",
        "sourceFile": "samples/twitter/tweet.js",
        "externalId": "1003"
      },
      "embedding": [
        0,
        0,
        0,
        0,
        0,
        0,
        0,
        0,
        0,
        0,
        0,
        0,
        0,
        0,
        0,
        0,
        0,
        0,
        0,
        0,
        0.279236,
        0,
        0,
        0,
        0.460739,
        0,
        0,
        0,
        0,
        0,
        0,
        0,
        0,
        0,
        0,
        0,
        0,
        0,
        0,
        0,
        0,
        0,
        0,
        0,
        0,
        0.279236,
        0,
        0,
        0,
        0,
        0,
        0,
        0,
        0,
        0,
        0,
        0,
        0,
        0.279236,
        0,
        0,
        0,
        0,
        0,
        0,
        0,
        0,
        0,
        0,
        0,
        0,
        0,
        0,
        0,
        0,
        0,
        0,
        0,
        0.097733,
        0,
        0.097733,
        0,
        0.097733,
        0,
        0,
        0,
        0,
        0,
        0,
        0,
        0,
        0,
        0,
        0,
        0,
        0,
        0,
        0,
        0,
        0,
        0,
        0,
        0,
        0,
        0,
        0,
        0,
        0,
        0,
        0,
        0,
        0,
        0,
        0,
        0,
        0,
        0,
        0,
        0,
        0,
        0,
        0,
        0,
        0,
        0,
        0,
        0,
        0,
        0,
        0,
        0,
        0,
        0,
        0,
        0,
        0,
        0,
        0,
        0,
        0,
        0,
        0,
        0,
        0,
        0,
        0,
        0,
        0,
        0,
        0,
        0,
        0,
        0,
        0,
        0,
        0,
        0,
        0,
        0,
        0,
        0,
        0.097733,
        0,
        0,
        0,
        0,
        0,
        0,
        0,
        0,
        0,
        0,
        0,
        0,
        0,
        0,
        0,
        0,
        0,
        0,
        0,
        0,
        0,
        0,
        0,
        0,
        0,
        0,
        0,
        0,
        0.279236,
        0,
        0,
        0,
        0,
        0,
        0,
        0,
        0,
        -0.279236,
        0,
        0,
        0,
        0,
        0,
        0,
        0,
        0,
        0,
        0,
        0.279236,
        0,
        0,
        0,
        0,
        0,
        0,
        0,
        0,
        0,
        0,
        0.097733,
        0,
        0,
        0,
        0,
        0,
        0,
        0,
        0,
        0,
        0,
        0,
        0,
        0,
        0,
        0,
        0.279236,
        0,
        0,
        0,
        0,
        0,
        0,
        0,
        0,
        0,
        0,
        0,
        0,
        0,
        0,
        0,
        0,
        0,
        0,
        0,
        0,
        0,
        0,
        0,
        0,
        0,
        0,
        0,
        0,
        0,
        0,
        0,
        0,
        0,
        -0.097733,
        0,
        0,
        0,
        0,
        0,
        0,
        0,
        0,
        0,
        0,
        0,
        -0.097733,
        0,
        0,
        0,
        0,
        0,
        0,
        0,
        0,
        0,
        0,
        0,
        0,
        0,
        0,
        0,
        0,
        0,
        0,
        0,
        0,
        0,
        0,
        0,
        0,
        0,
        0,
        0,
        0,
        0,
        0,
        0,
        0,
        0,
        0,
        0,
        -0.097733,
        0,
        0,
        0,
        0,
        0,
        0,
        0,
        0.279236,
        0,
        0,
        0,
        0,
        0,
        0,
        0,
        0,
        0,
        0,
        0,
        0,
        0,
        0,
        0,
        0,
        0,
        0,
        0,
        0,
        0,
        0,
        0,
        0,
        0,
        0,
        0,
        0,
        0,
        0,
        0,
        0,
        0,
        0,
        0,
        0,
        0,
        0,
        -0.279236,
        0,
        0,
        0,
        0,
        0,
        0,
        0,
        0,
        0,
        0,
        0.097733,
        0,
        0,
        0,
        0,
        0,
        0
      ],
      "embeddingModel": "local-hashing-v1",
      "embeddingDimensions": 384,
      "insertedAt": "2026-06-03T13:28:15.120Z"
    },
    {
      "id": "chunk_83351ff1d39c8100cc4ccb8f",
      "documentId": "instagram_6f8e1833bea9c4824926877b",
      "personId": "sample-person",
      "platform": "instagram",
      "kind": "caption",
      "text": "My favorite remote setup is boring: clear priorities, fewer meetings, and a written handoff.",
      "ordinal": 0,
      "tokenCount": 11,
      "contentHash": "83351ff1d39c8100cc4ccb8f",
      "authoredAt": "2025-01-10T12:00:00.000Z",
      "uri": "media/posts/202501/remote-desk.jpg",
      "sourceTitle": "Instagram caption",
      "metadata": {
        "mediaPath": "media/posts/202501/remote-desk.jpg",
        "sourceFile": "samples/instagram/posts_1.json",
        "externalId": "media/posts/202501/remote-desk.jpg"
      },
      "embedding": [
        0,
        0,
        0,
        0,
        0,
        0,
        0,
        -0.109455,
        0,
        0,
        0,
        0,
        0,
        0,
        0,
        0,
        0,
        -0.109455,
        -0.312729,
        0,
        0,
        0,
        0,
        0,
        0,
        0,
        0,
        0,
        0,
        0,
        0,
        0,
        0,
        0,
        0,
        0,
        0.109455,
        0,
        0.109455,
        0.109455,
        0,
        0,
        0,
        0,
        0,
        0,
        0,
        0,
        0,
        0,
        0,
        0,
        0,
        0,
        0,
        0,
        0,
        0,
        0,
        0,
        0,
        0,
        0,
        0,
        -0.312729,
        0,
        0,
        0,
        0,
        0,
        0,
        0,
        0,
        0,
        0,
        0,
        0,
        0,
        0,
        0,
        0,
        0,
        0,
        0,
        0,
        0,
        0,
        0,
        0,
        0,
        0,
        0,
        0,
        0,
        0,
        0,
        0,
        0,
        0,
        0,
        0,
        0,
        0,
        0,
        0,
        0,
        0,
        -0.312729,
        0,
        0,
        0,
        0,
        0,
        0,
        0,
        0,
        0,
        0,
        0,
        0,
        0.109455,
        0,
        0,
        0,
        0,
        0,
        0,
        0,
        0,
        0,
        0,
        0,
        0,
        0,
        0,
        0,
        0,
        0,
        0,
        0,
        0,
        -0.109455,
        0,
        0,
        0,
        0,
        0,
        0.312729,
        0,
        0,
        0,
        0,
        0,
        -0.109455,
        0,
        0,
        0,
        0,
        0,
        0,
        0,
        0,
        0,
        0,
        0,
        0,
        0,
        0,
        0,
        0,
        0,
        0,
        0,
        0,
        0,
        0,
        0,
        0,
        0,
        0,
        -0.312729,
        0,
        0.312729,
        0,
        0,
        0,
        0,
        0,
        0,
        0,
        0,
        0,
        0,
        0,
        0,
        0,
        0,
        0,
        0,
        0,
        0,
        0,
        0,
        0,
        0,
        0.312729,
        0,
        0,
        0,
        0,
        0,
        -0.312729,
        0,
        0,
        0,
        0,
        0,
        0,
        0,
        -0.109455,
        0,
        0,
        0,
        0,
        0,
        0,
        0,
        0,
        0,
        0,
        0,
        0,
        0,
        0,
        0,
        0,
        0,
        0,
        0,
        0,
        0,
        0,
        0,
        0,
        0,
        0,
        0,
        0,
        0,
        0,
        0,
        0,
        0,
        0,
        0,
        0,
        0,
        0,
        0,
        0,
        0,
        0,
        0.109455,
        0,
        0,
        0,
        0,
        0,
        0,
        0,
        0,
        0,
        0,
        0,
        0,
        0,
        0,
        0,
        0,
        0,
        0,
        0,
        0,
        0,
        0,
        0,
        0,
        0,
        0,
        0,
        0.312729,
        0,
        0,
        0,
        0,
        0,
        0,
        0,
        0,
        0,
        0,
        0,
        0,
        0,
        0,
        0,
        0,
        0,
        0,
        0,
        0,
        0,
        0,
        0,
        0,
        0,
        0,
        0,
        0,
        0,
        0,
        0,
        0,
        0,
        0,
        0,
        0,
        0,
        0,
        0,
        0,
        0,
        0,
        0,
        0,
        0,
        0,
        0,
        0,
        0,
        0,
        0,
        0,
        0,
        0,
        0,
        0,
        0,
        0,
        0,
        0,
        0,
        0,
        0,
        0,
        0,
        0,
        0,
        0,
        0,
        0,
        0,
        0,
        0,
        0,
        0,
        0,
        0,
        0,
        0,
        0,
        0,
        0,
        0,
        0,
        0,
        0,
        0,
        0,
        0,
        0,
        0,
        0,
        0
      ],
      "embeddingModel": "local-hashing-v1",
      "embeddingDimensions": 384,
      "insertedAt": "2026-06-03T13:28:15.120Z"
    },
    {
      "id": "chunk_467f365f991f90f79e6ced9c",
      "documentId": "instagram_a30adb37ebf70c844faea47e",
      "personId": "sample-person",
      "platform": "instagram",
      "kind": "caption",
      "text": "Offsites are useful for relationships, not for pretending every day needs to be in person.",
      "ordinal": 0,
      "tokenCount": 8,
      "contentHash": "467f365f991f90f79e6ced9c",
      "authoredAt": "2025-02-10T12:00:00.000Z",
      "uri": "media/posts/202502/team-offsite.jpg",
      "sourceTitle": "Instagram caption",
      "metadata": {
        "mediaPath": "media/posts/202502/team-offsite.jpg",
        "sourceFile": "samples/instagram/posts_1.json",
        "externalId": "media/posts/202502/team-offsite.jpg"
      },
      "embedding": [
        0,
        0,
        0,
        0,
        0,
        0,
        0,
        0,
        0,
        0,
        0,
        0,
        0,
        0,
        0,
        0,
        0,
        0,
        0,
        0,
        0,
        0,
        0,
        0,
        0,
        0,
        0,
        0,
        0,
        0.117601,
        0,
        0,
        0,
        0,
        0,
        0,
        0,
        0,
        0,
        0,
        0,
        0,
        0,
        0,
        0,
        0,
        0,
        0.336004,
        0,
        0,
        0,
        0,
        0,
        0.117601,
        0,
        0,
        0,
        0,
        -0.336004,
        0,
        0,
        0,
        0,
        0,
        0,
        0,
        0,
        0,
        0,
        0,
        0,
        0,
        0,
        0,
        -0.117601,
        0,
        0,
        0,
        0,
        0,
        0,
        0,
        0,
        0,
        0,
        0,
        0,
        0,
        0,
        0,
        0,
        0,
        0,
        0,
        0,
        0,
        0,
        0,
        0,
        0,
        0,
        0,
        0,
        0,
        0,
        0,
        0,
        0,
        0,
        0,
        0,
        0,
        0,
        0,
        0,
        0,
        0,
        0,
        0,
        0,
        0,
        0,
        0,
        0,
        0,
        -0.336004,
        0,
        0,
        0,
        0,
        0,
        0,
        0,
        0,
        0,
        0,
        0,
        0,
        0,
        0,
        0,
        0,
        0,
        -0.117601,
        0,
        0,
        0,
        0,
        0,
        0,
        0,
        0.117601,
        0,
        0,
        0,
        0,
        0,
        0,
        0.336004,
        0,
        0,
        0,
        0,
        0,
        0,
        0,
        0,
        0,
        0,
        0,
        0,
        0,
        0,
        0,
        0,
        0,
        0,
        0,
        0,
        0,
        0,
        0,
        0,
        0,
        0,
        0.117601,
        0,
        0,
        0,
        0,
        0,
        0,
        0,
        0,
        0,
        0,
        0,
        0,
        0,
        0,
        0,
        0,
        0,
        0,
        0,
        0,
        0,
        0,
        0,
        0,
        0,
        0,
        0,
        0,
        0,
        0,
        0,
        0,
        0,
        0,
        0,
        0,
        0,
        0,
        0,
        0,
        0,
        0,
        0,
        0,
        0,
        0,
        0,
        0,
        0,
        0,
        0,
        0,
        0,
        0,
        0,
        0,
        0,
        0,
        0,
        0,
        0,
        0,
        0,
        0,
        0,
        0,
        0,
        0,
        0,
        0,
        0,
        0,
        0,
        0,
        0.336004,
        0,
        0,
        -0.117601,
        0,
        0,
        0.336004,
        0,
        0,
        0,
        0,
        0,
        0,
        0,
        0,
        0,
        0,
        0,
        0,
        0,
        0,
        0,
        0,
        0,
        0,
        0,
        0,
        0,
        0,
        0,
        0,
        0,
        0,
        0,
        0,
        0,
        0,
        0,
        0,
        0,
        0,
        0,
        0,
        0,
        0,
        0,
        0,
        0,
        0,
        0,
        0,
        0,
        0,
        0,
        0,
        0,
        0,
        0,
        0,
        0,
        0,
        0,
        0,
        0,
        0,
        0.336004,
        0,
        0,
        0,
        0,
        0,
        0,
        0,
        0,
        0,
        0,
        0,
        0,
        0,
        0,
        0,
        0,
        0,
        0,
        0.336004,
        0,
        0,
        0,
        0,
        0,
        0,
        0,
        0,
        0,
        0,
        0,
        0,
        0,
        0,
        0,
        0,
        0,
        0,
        0,
        0,
        0,
        0,
        0,
        0,
        0,
        0,
        0,
        0,
        0,
        0,
        0,
        0,
        0,
        0,
        0,
        0,
        0,
        0,
        0
      ],
      "embeddingModel": "local-hashing-v1",
      "embeddingDimensions": 384,
      "insertedAt": "2026-06-03T13:28:15.120Z"
    }
  ]
}